<?xml version="1.0" encoding="UTF-8"?>
<!-- THIS is a file generated by db_generator, Please not modify -->
<!-- Authored by USTC 2010 SOFTWARE TEAM BIONOVO -->
<MoDeL>
	<dbInterface>
		<input>
			<listOfCompartments>
				<compartment db="Flask">
					<id>Flask</id>
					<size>0.40</size>
					<outside>ROOT</outside>
					<constant>true</constant>
				</compartment>
				<compartment db="E_coli">
					<id>E_coli</id>
					<size>1E-14</size>
					<outside>Flask</outside>
					<constant>true</constant>
				</compartment>
			</listOfCompartments>
			<listOfSpecies>
				<species>
					<id>sPecIes0</id>
					<compartment itself="E_coli">Flask</compartment>
					<initialConcentration>1E-20</initialConcentration>
					<substanceUnits>mole</substanceUnits>
					<cnModel>
						<listOfChains>
							<chain>
								<listOfParts>
									<part>
										<partReference>E_coli</partReference>
										<partLabel>E_coli_0</partLabel>
										<partType>Compartment</partType>
										<partCategory>compartment</partCategory>
									</part>
								</listOfParts>
							</chain>
						</listOfChains>
					</cnModel>
				</species>
				<species>
					<id>sPecIes1</id>
					<compartment>E_coli</compartment>
					<initialAmount>1E-22</initialAmount>
					<substanceUnits>mole</substanceUnits>
					<cnModel>
						<listOfChains>
							<chain>
								<listOfParts>
									<part>
										<partReference>pSB1A3</partReference>
										<partLabel>pSB1A3_0</partLabel>
										<partType>ForwardDNA</partType>
										<partCategory>biobrick</partCategory>
									</part>
									<part>
										<partReference>TE_X_100</partReference>
										<partLabel>TE_X_100_0</partLabel>
										<partType>ForwardDNA</partType>
										<partCategory>biobrick</partCategory>
									</part>
									<part>
										<partReference>placI185</partReference>
										<partLabel>placI185_0</partLabel>
										<partType>ForwardDNA</partType>
										<partCategory>biobrick</partCategory>
									</part>
									<part>
										<partReference>RBS147</partReference>
										<partLabel>RBS147_1</partLabel>
										<partType>ForwardDNA</partType>
										<partCategory>biobrick</partCategory>
									</part>
									<part>
										<partReference>lacI153</partReference>
										<partLabel>lacI153_0</partLabel>
										<partType>ForwardDNA</partType>
										<partCategory>biobrick</partCategory>
									</part>
									<part>
										<partReference>TE_X_100</partReference>
										<partLabel>TE_X_100_1</partLabel>
										<partType>ForwardDNA</partType>
										<partCategory>biobrick</partCategory>
									</part>
								</listOfParts>
							</chain>
						</listOfChains>
					</cnModel>
				</species>
			</listOfSpecies>
		</input>
	</dbInterface>
</MoDeL>
